<GeoServerTileLayer>
  <id>LayerInfoImpl-5dc13696:18f3f1d64ac:-7fff</id>
  <enabled>true</enabled>
  <inMemoryCached>true</inMemoryCached>
  <name>Tarif_de_cubage:regions</name>
  <mimeFormats>
    <string>image/jpeg</string>
    <string>image/png</string>
  </mimeFormats>
  <gridSubsets>
    <gridSubset>
      <gridSetName>EPSG:900913</gridSetName>
      <extent>
        <coords>
          <double>-1904115.167909197</double>
          <double>2364653.349857575</double>
          <double>-111181.24062648973</double>
          <double>4289953.369848222</double>
        </coords>
      </extent>
    </gridSubset>
    <gridSubset>
      <gridSetName>EPSG:4326</gridSetName>
      <extent>
        <coords>
          <double>-17.104957580566406</double>
          <double>20.771501541137695</double>
          <double>-0.99875807762146</double>
          <double>35.92243194580078</double>
        </coords>
      </extent>
    </gridSubset>
  </gridSubsets>
  <metaWidthHeight>
    <int>4</int>
    <int>4</int>
  </metaWidthHeight>
  <expireCache>0</expireCache>
  <expireClients>0</expireClients>
  <parameterFilters>
    <styleParameterFilter>
      <key>STYLES</key>
      <defaultValue></defaultValue>
      <availableStyles class="sorted-set"/>
      <defaultStyle>Tarif_de_cubage:region_style</defaultStyle>
    </styleParameterFilter>
  </parameterFilters>
  <gutter>0</gutter>
  <cacheWarningSkips/>
</GeoServerTileLayer>